simtables/__init__.py
simtables/record.py
simtables/table.py
simtables-0.1.0.dist-info/DESCRIPTION.rst
simtables-0.1.0.dist-info/METADATA
simtables-0.1.0.dist-info/RECORD
simtables-0.1.0.dist-info/WHEEL
simtables-0.1.0.dist-info/metadata.json
simtables-0.1.0.dist-info/top_level.txt
