Metadata-Version: 2.0
Name: simtables
Version: 0.1.0
Summary: Simple tables
Home-page: https://github.com/achambers8472/simtables
Author: Alexander Chambers
Author-email: alexander.chambers8472@gmail.com
License: UNKNOWN
Platform: UNKNOWN
Classifier: Programming Language :: Python :: 3
Classifier: License :: OSI Approved :: MIT License
Classifier: Operating System :: OS Independent
